cnm/__init__.py
cnm/shell/__init__.py
cnm/shell/usage.py
cnm/src/temp.txt
package_name/__init__.py
package_name/shell/__init__.py
package_name/shell/usage.py
package_name/src/temp.txt
cnm-0.0.1.dist-info/LICENSE
cnm-0.0.1.dist-info/METADATA
cnm-0.0.1.dist-info/WHEEL
cnm-0.0.1.dist-info/entry_points.txt
cnm-0.0.1.dist-info/top_level.txt
cnm-0.0.1.dist-info/zip-safe
cnm-0.0.1.dist-info/RECORD
